{
  "lastUpdated": "2026-02-14T15:26:54Z",
  "sites": [
    {
      "name": "L'heure des comptes",
      "currentStatus": "up",
      "days": [
        {
          "date": "2026-02-08",
          "total": 38,
          "ok": 38,
          "responseTimeSum": 6670,
          "uptime": 100,
          "responseTime": 175.52631578947367
        },
        {
          "date": "2026-02-09",
          "total": 48,
          "ok": 48,
          "responseTimeSum": 9479,
          "uptime": 100,
          "responseTime": 197.47916666666666
        },
        {
          "date": "2026-02-10",
          "total": 49,
          "ok": 49,
          "responseTimeSum": 9592,
          "uptime": 100,
          "responseTime": 195.75510204081633
        },
        {
          "date": "2026-02-11",
          "total": 51,
          "ok": 51,
          "responseTimeSum": 9698,
          "uptime": 100,
          "responseTime": 190.15686274509804
        },
        {
          "date": "2026-02-12",
          "total": 55,
          "ok": 55,
          "responseTimeSum": 10550,
          "uptime": 100,
          "responseTime": 191.8181818181818
        },
        {
          "date": "2026-02-13",
          "total": 59,
          "ok": 59,
          "responseTimeSum": 11356,
          "uptime": 100,
          "responseTime": 192.47457627118644
        },
        {
          "date": "2026-02-14",
          "total": 44,
          "ok": 44,
          "responseTimeSum": 8036,
          "uptime": 100,
          "responseTime": 182.63636363636363
        }
      ]
    },
    {
      "name": "API",
      "currentStatus": "up",
      "days": [
        {
          "date": "2026-02-08",
          "total": 38,
          "ok": 38,
          "responseTimeSum": 4949,
          "uptime": 100,
          "responseTime": 130.23684210526315
        },
        {
          "date": "2026-02-09",
          "total": 48,
          "ok": 48,
          "responseTimeSum": 7298,
          "uptime": 100,
          "responseTime": 152.04166666666666
        },
        {
          "date": "2026-02-10",
          "total": 49,
          "ok": 49,
          "responseTimeSum": 6662,
          "uptime": 100,
          "responseTime": 135.9591836734694
        },
        {
          "date": "2026-02-11",
          "total": 51,
          "ok": 51,
          "responseTimeSum": 6934,
          "uptime": 100,
          "responseTime": 135.9607843137255
        },
        {
          "date": "2026-02-12",
          "total": 55,
          "ok": 55,
          "responseTimeSum": 7411,
          "uptime": 100,
          "responseTime": 134.74545454545455
        },
        {
          "date": "2026-02-13",
          "total": 59,
          "ok": 59,
          "responseTimeSum": 7837,
          "uptime": 100,
          "responseTime": 132.83050847457628
        },
        {
          "date": "2026-02-14",
          "total": 44,
          "ok": 44,
          "responseTimeSum": 5682,
          "uptime": 100,
          "responseTime": 129.13636363636363
        }
      ]
    },
    {
      "name": "Carte interactive (embed)",
      "currentStatus": "up",
      "days": [
        {
          "date": "2026-02-08",
          "total": 38,
          "ok": 38,
          "responseTimeSum": 5177,
          "uptime": 100,
          "responseTime": 136.23684210526315
        },
        {
          "date": "2026-02-09",
          "total": 48,
          "ok": 48,
          "responseTimeSum": 8329,
          "uptime": 100,
          "responseTime": 173.52083333333334
        },
        {
          "date": "2026-02-10",
          "total": 49,
          "ok": 49,
          "responseTimeSum": 6970,
          "uptime": 100,
          "responseTime": 142.24489795918367
        },
        {
          "date": "2026-02-11",
          "total": 51,
          "ok": 51,
          "responseTimeSum": 7456,
          "uptime": 100,
          "responseTime": 146.19607843137254
        },
        {
          "date": "2026-02-12",
          "total": 55,
          "ok": 55,
          "responseTimeSum": 7911,
          "uptime": 100,
          "responseTime": 143.83636363636364
        },
        {
          "date": "2026-02-13",
          "total": 59,
          "ok": 59,
          "responseTimeSum": 8674,
          "uptime": 100,
          "responseTime": 147.01694915254237
        },
        {
          "date": "2026-02-14",
          "total": 44,
          "ok": 44,
          "responseTimeSum": 6005,
          "uptime": 100,
          "responseTime": 136.47727272727272
        }
      ]
    }
  ]
}
